<?xml version="1.0" encoding="utf-8"?>
<odoo>
    <data noupdate="1">
        <record id="hmi_user_role_anony" model="oneshare.hmi.user.role">
            <field name="name">匿名用户</field>
            <field name="code">anonymous</field>
        </record>
        <record id="hmi_user_role_admin" model="oneshare.hmi.user.role">
            <field name="name">管理员</field>
            <field name="code">admin</field>
        </record>
        <record id="hmi_user_role_user" model="oneshare.hmi.user.role">
            <field name="name">操作员</field>
            <field name="code">user</field>
        </record>

    </data>
</odoo>